Metadata-Version: 2.1
Name: apisnote
Version: 0.0.5
Summary: api note by cemiix
Home-page: https://apis.kgbot.pp.ua/docs/home
Author: cemiix
Author-email: maks.ivan4enko@gmail.com
License: Apache License, Version 2.0, see LICENSE file
Download-URL: https://github.com/Cemiix/apinote/archive/master.zip
Keywords: apisnote,note
Platform: UNKNOWN
Classifier: License :: OSI Approved :: Apache Software License
Classifier: Operating System :: OS Independent
Classifier: Environment :: Console
Classifier: Development Status :: 3 - Alpha
Classifier: Programming Language :: Python
Classifier: Programming Language :: Python :: 3
Classifier: Programming Language :: Python :: 3.6
Classifier: Programming Language :: Python :: 3.7
Classifier: Programming Language :: Python :: 3.8
Classifier: Programming Language :: Python :: 3.9
Classifier: Programming Language :: Python :: 3 :: Only
Classifier: Programming Language :: Python :: Implementation :: PyPy
